odoo/addons/l10n_br_delivery/README.rst
odoo/addons/l10n_br_delivery/__init__.py
odoo/addons/l10n_br_delivery/__manifest__.py
odoo/addons/l10n_br_delivery/data/account_incoterms_data.xml
odoo/addons/l10n_br_delivery/data/res_config_settings_data.xml
odoo/addons/l10n_br_delivery/demo/l10n_br_delivery_demo.xml
odoo/addons/l10n_br_delivery/demo/sale_order_demo.xml
odoo/addons/l10n_br_delivery/i18n/l10n_br_delivery.pot
odoo/addons/l10n_br_delivery/i18n/pt_BR.po
odoo/addons/l10n_br_delivery/models/__init__.py
odoo/addons/l10n_br_delivery/models/account_incoterms.py
odoo/addons/l10n_br_delivery/models/delivery_carrier.py
odoo/addons/l10n_br_delivery/models/document_mixin.py
odoo/addons/l10n_br_delivery/models/sale_order.py
odoo/addons/l10n_br_delivery/models/stock_picking.py
odoo/addons/l10n_br_delivery/models/vehicle.py
odoo/addons/l10n_br_delivery/readme/CONFIGURE.md
odoo/addons/l10n_br_delivery/readme/CONTRIBUTORS.md
odoo/addons/l10n_br_delivery/readme/DESCRIPTION.md
odoo/addons/l10n_br_delivery/readme/HISTORY.md
odoo/addons/l10n_br_delivery/readme/INSTALL.md
odoo/addons/l10n_br_delivery/readme/ROADMAP.md
odoo/addons/l10n_br_delivery/readme/USAGE.md
odoo/addons/l10n_br_delivery/security/ir.model.access.csv
odoo/addons/l10n_br_delivery/static/description/icon.png
odoo/addons/l10n_br_delivery/static/description/index.html
odoo/addons/l10n_br_delivery/tests/__init__.py
odoo/addons/l10n_br_delivery/tests/test_delivery_inverse_amount.py
odoo/addons/l10n_br_delivery/views/account_incoterms_view.xml
odoo/addons/l10n_br_delivery/views/delivery_carrier_views.xml
odoo/addons/l10n_br_delivery/views/l10n_br_delivery_view.xml
odoo/addons/l10n_br_delivery/views/sale_order_view.xml
odoo/addons/l10n_br_delivery/views/stock_picking_view.xml
odoo_addon_l10n_br_delivery-16.0.4.0.0.1.dist-info/METADATA
odoo_addon_l10n_br_delivery-16.0.4.0.0.1.dist-info/WHEEL
odoo_addon_l10n_br_delivery-16.0.4.0.0.1.dist-info/top_level.txt
odoo_addon_l10n_br_delivery-16.0.4.0.0.1.dist-info/RECORD
